{
  "items": [
    {
      "sys": { "id": "1" },
      "fields": {
        "name": "Arianne Arias",
        "title": "URBAN BEAUTY REP",
        "reviews": "Lorem ipsum dolor sit amet consectetur adipisicing elit.",
        "image": { "fields": { "file": { "url": "/src/assets/images/landing/vip-rep-1.jpg" } } }
      }
    },
    {
      "sys": { "id": "2" },
      "fields": {
        "name": "Kai Croft",
        "title": "MORTAR & PESTLE REP",
        "reviews": "Ut laborum iste sit excepturi reiciendis non quis consequatur a consequatur?",
        "image": { "fields": { "file": { "url": "/src/assets/images/landing/vip-rep-2.jpg" } } }
      }
    },
    {
      "sys": { "id": "3" },
      "fields": {
        "name": "Sasha Curry",
        "title": "INSTITUTE REP",
        "reviews": "Nam quibusdam incidunt qui porro beatae sed galisum neque.",
        "image": { "fields": { "file": { "url": "/src/assets/images/landing/vip-rep-3.jpg" } } }
      }
    },
    {
      "sys": { "id": "4" },
      "fields": {
        "name": "Danica Mcneill",
        "title": "YES SAN LAURA REP",
        "reviews": "Eum rerum corporis sed possimus error aut cumque suscipit qui.",
        "image": { "fields": { "file": { "url": "/src/assets/images/landing/vip-rep-4.jpg" } } }
      }
    },
    {
      "sys": { "id": "5" },
      "fields": {
        "name": "Destiny Wilkerson",
        "title": "SWEETEST ROSE REP",
        "reviews": "Est nesciunt nostrum est reprehenderit consequatur et molestiae nihil.",
        "image": { "fields": { "file": { "url": "/src/assets/images/landing/vip-rep-5.jpg" } } }
      }
    },
    {
      "sys": { "id": "6" },
      "fields": {
        "name": "Tierney Horner",
        "title": "THE ORDINARY REP",
        "reviews": "Qui asperiores impedit id quaerat omnis aut assumenda omnis?",
        "image": { "fields": { "file": { "url": "/src/assets/images/landing/vip-rep-6.jpg" } } }
      }
    },
    {
      "sys": { "id": "7" },
      "fields": {
        "name": "Maddy Braun",
        "title": "MARA O. JOSEPH REP",
        "reviews": "Et distinctio animi non quia galisum ea exercitationem delectus.",
        "image": { "fields": { "file": { "url": "/src/assets/images/landing/vip-rep-7.jpg" } } }
      }
    },
    {
      "sys": { "id": "8" },
      "fields": {
        "name": "Kay Dejesus",
        "title": "BOCCA REP",
        "reviews": "Qui error sint atque laborum sed sequi voluptatibus aut voluptas quia.",
        "image": { "fields": { "file": { "url": "/src/assets/images/landing/vip-rep-8.jpg" } } }
      }
    },
    {
      "sys": { "id": "9" },
      "fields": {
        "name": "Anwar Mcconnell",
        "title": "VENUS REP",
        "reviews": "Id molestias modi hic voluptatem voluptates quo voluptatem corrupti.",
        "image": { "fields": { "file": { "url": "/src/assets/images/landing/vip-rep-9.jpg" } } }
      }
    }
  ]
}
